peelml/__init__.py
peelml/cli.py
peelml/client/.gitignore
peelml/client/.npmrc
peelml/client/README.md
peelml/client/build/_app/immutable/assets/0.fd99616d.css
peelml/client/build/_app/immutable/assets/5.8f04d108.css
peelml/client/build/_app/immutable/assets/6.98c9af80.css
peelml/client/build/_app/immutable/assets/7.6f6c636b.css
peelml/client/build/_app/immutable/assets/8.a14237ec.css
peelml/client/build/_app/immutable/assets/9.6d9bf5de.css
peelml/client/build/_app/immutable/assets/_layout.fd99616d.css
peelml/client/build/_app/immutable/assets/_page.6d9bf5de.css
peelml/client/build/_app/immutable/assets/_page.6f6c636b.css
peelml/client/build/_app/immutable/assets/_page.8f04d108.css
peelml/client/build/_app/immutable/assets/_page.98c9af80.css
peelml/client/build/_app/immutable/assets/_page.a14237ec.css
peelml/client/build/_app/immutable/assets/github.1ea8d62e.svg
peelml/client/build/_app/immutable/assets/logo.8b972bb6.svg
peelml/client/build/_app/immutable/chunks/UploadFiles.20ed0f81.js
peelml/client/build/_app/immutable/chunks/environment.9aa685ef.js
peelml/client/build/_app/immutable/chunks/index.463cc238.js
peelml/client/build/_app/immutable/chunks/index.6ec942b9.js
peelml/client/build/_app/immutable/chunks/logo.8522a027.js
peelml/client/build/_app/immutable/chunks/singletons.92741890.js
peelml/client/build/_app/immutable/chunks/store.4903bc61.js
peelml/client/build/_app/immutable/chunks/utils.12623cfb.js
peelml/client/build/_app/immutable/entry/app.59904e1c.js
peelml/client/build/_app/immutable/entry/start.0de09a63.js
peelml/client/build/_app/immutable/nodes/0.527974e2.js
peelml/client/build/_app/immutable/nodes/1.79848fd6.js
peelml/client/build/_app/immutable/nodes/10.758b2886.js
peelml/client/build/_app/immutable/nodes/11.758b2886.js
peelml/client/build/_app/immutable/nodes/12.acf3ba70.js
peelml/client/build/_app/immutable/nodes/13.a5b47bbf.js
peelml/client/build/_app/immutable/nodes/14.2e678f15.js
peelml/client/build/_app/immutable/nodes/15.0c5d77af.js
peelml-0.0.4.dist-info/LICENSE.txt
peelml-0.0.4.dist-info/METADATA
peelml-0.0.4.dist-info/WHEEL
peelml-0.0.4.dist-info/entry_points.txt
peelml-0.0.4.dist-info/RECORD
