Metadata-Version: 2.1
Name: peelml
Version: 0.0.4
Summary: Peel away the pain of ml deployment
Author: Rachel Hu
Author-email: goldpiggy@berkeley.edu
Maintainer: Jared Wilber
Maintainer-email: jdwlbr@gmail.com
Requires-Python: >=3.9,<4.0
Classifier: Programming Language :: Python :: 3
Classifier: Programming Language :: Python :: 3.9
Classifier: Programming Language :: Python :: 3.10
Classifier: Programming Language :: Python :: 3.11
Requires-Dist: boto3 (==1.26.165)
Requires-Dist: chromadb (==0.3.26)
Requires-Dist: click (==8.0.4)
Requires-Dist: docx2txt (==0.8)
Requires-Dist: duckdb (==0.8.1)
Requires-Dist: fastapi (==0.100.0)
Requires-Dist: flask (==2.2.3)
Requires-Dist: flask-cors (==4.0.0)
Requires-Dist: inquirer (==3.1.3)
Requires-Dist: langchain (==0.0.220)
Requires-Dist: llama-cpp-python (==0.1.66)
Requires-Dist: llvmlite (==0.40.1)
Requires-Dist: numba (==0.57.1)
Requires-Dist: openai (==0.27.8)
Requires-Dist: pdfminer-six (==20221105)
Requires-Dist: poetry (==1.4.2)
Requires-Dist: pydantic (==1.10.11)
Requires-Dist: python-dotenv (==1.0.0)
Requires-Dist: sagemaker (==2.169.0)
Requires-Dist: scikit-learn (==1.3.0)
Requires-Dist: starlette (==0.27.0)
Requires-Dist: tiktoken (==0.4.0)
Requires-Dist: tokenizers (==0.13.3)
Requires-Dist: typer (==0.9.0)
Requires-Dist: umap (==0.1.1)
Requires-Dist: umap-learn (==0.5.3)
Requires-Dist: virtualenv (==20.16.5)
